crump/__init__.py
crump/cdf_extractor.py
crump/cdf_reader.py
crump/cli.py
crump/cli_extract.py
crump/cli_inspect.py
crump/cli_prepare.py
crump/cli_sync.py
crump/config.py
crump/console_utils.py
crump/csv_file.py
crump/database.py
crump/file_types.py
crump/history.py
crump/parquet_file.py
crump/tabular_file.py
crump/type_detection.py
crump-0.3.0.dist-info/METADATA
crump-0.3.0.dist-info/WHEEL
crump-0.3.0.dist-info/entry_points.txt
crump-0.3.0.dist-info/licenses/LICENSE
crump-0.3.0.dist-info/RECORD
