Metadata-Version: 2.4
Name: crump
Version: 0.3.0
Summary: Csv/cdf Read and dUMP - Sync CSV, Parquet, and CDF science files into PostgreSQL database
Author-email: Alastair Crabtree <a.crabtree@imperial.ac.uk>
License-Expression: MIT
License-File: LICENSE
Classifier: Development Status :: 3 - Alpha
Classifier: Intended Audience :: Developers
Classifier: License :: OSI Approved :: MIT License
Classifier: Programming Language :: Python :: 3
Classifier: Programming Language :: Python :: 3.11
Classifier: Programming Language :: Python :: 3.12
Classifier: Programming Language :: Python :: 3.13
Classifier: Programming Language :: Python :: 3.14
Requires-Python: >=3.11
Requires-Dist: cdflib>=1.3.6
Requires-Dist: click>=8.1.7
Requires-Dist: psycopg[binary]>=3.1.0
Requires-Dist: pyarrow>=18.0.0
Requires-Dist: pyyaml>=6.0.1
Requires-Dist: rich>=13.7.0
Provides-Extra: dev
Requires-Dist: mkdocs-autorefs>=0.5.0; extra == 'dev'
Requires-Dist: mkdocs-material>=9.5.0; extra == 'dev'
Requires-Dist: mkdocs>=1.5.0; extra == 'dev'
Requires-Dist: mypy>=1.8.0; extra == 'dev'
Requires-Dist: pytest-cov>=4.1.0; extra == 'dev'
Requires-Dist: pytest-mock>=3.12.0; extra == 'dev'
Requires-Dist: pytest>=8.0.0; extra == 'dev'
Requires-Dist: ruff>=0.1.0; extra == 'dev'
Requires-Dist: testcontainers[postgresql]>=4.0.0; extra == 'dev'
